s3_saver.py
s3_saver-0.1.4.dist-info/RECORD
s3_saver-0.1.4.dist-info/DESCRIPTION.rst
s3_saver-0.1.4.dist-info/top_level.txt
s3_saver-0.1.4.dist-info/METADATA
s3_saver-0.1.4.dist-info/WHEEL
s3_saver-0.1.4.dist-info/metadata.json
