Metadata-Version: 2.0
Name: s3-saver
Version: 0.1.4
Summary: Utility class in Python for finding, saving, and deleting files that are either on Amazon S3, or on the local filesystem.
Home-page: https://github.com/Jaza/s3-saver
Author: Jeremy Epstein
Author-email: jazepstein@gmail.com
License: UNKNOWN
Platform: any
Classifier: Development Status :: 2 - Pre-Alpha
Classifier: Environment :: Web Environment
Classifier: Intended Audience :: Developers
Classifier: Operating System :: OS Independent
Classifier: Programming Language :: Python
Classifier: Programming Language :: Python :: 2
Classifier: Programming Language :: Python :: 2.7
Classifier: Programming Language :: Python :: 3
Classifier: Programming Language :: Python :: 3.3
Requires-Dist: boto
